{"1":{"ID":1,"Class":1,"String_ID":2039,"Attack":462.5,"Defend":212.5,"HP":4500,"Crit":500,"Crit_Damage":900,"Dodge":300,"Speed":2.9,"DMG":9,"DEF":5,"SPD":6,"CC":6,"SUP":2,"Skill":[1101,1102,1103,1104],"Hp_Height":1.9,"Face_Height":1.35,"Jump_Speed":1,"Story_StringID":0,"Model":""},"2":{"ID":2,"Class":2,"String_ID":2040,"Attack":475,"Defend":200,"HP":4250,"Crit":360,"Crit_Damage":700,"Dodge":240,"Speed":2.9,"DMG":6,"DEF":6,"SPD":6,"CC":6,"SUP":4,"Skill":[1201,1202,1203,1204],"Hp_Height":1.9,"Face_Height":1.5,"Jump_Speed":1,"Story_StringID":0,"Model":""},"3":{"ID":3,"Class":3,"String_ID":2041,"Attack":500,"Defend":250,"HP":5000,"Crit":300,"Crit_Damage":700,"Dodge":360,"Speed":3.5,"DMG":6,"DEF":7,"SPD":4,"CC":4,"SUP":6,"Skill":[1301,1302,1303,1304],"Hp_Height":2.1,"Face_Height":1.7,"Jump_Speed":1,"Story_StringID":0,"Model":""},"4":{"ID":4,"Class":4,"String_ID":2042,"Attack":550,"Defend":225,"HP":4250,"Crit":400,"Crit_Damage":800,"Dodge":180,"Speed":2.5,"DMG":10,"DEF":4,"SPD":4,"CC":4,"SUP":4,"Skill":[1401,1402,1403,1404],"Hp_Height":1.3,"Face_Height":0.9,"Jump_Speed":1,"Story_StringID":0,"Model":""},"5":{"ID":5,"Class":5,"String_ID":2043,"Attack":450,"Defend":275,"HP":5500,"Crit":440,"Crit_Damage":600,"Dodge":200,"Speed":3.5,"DMG":6,"DEF":9,"SPD":8,"CC":2,"SUP":9,"Skill":[1501,1502,1503,1504],"Hp_Height":2.2,"Face_Height":1.75,"Jump_Speed":1,"Story_StringID":0,"Model":""}}